django_queue/__init__.py
django_queue/admin.py
django_queue/apps.py
django_queue/models.py
django_queue/tests.py
django_queue/views.py
django_queue/migrations/0001_initial.py
django_queue/migrations/__init__.py
django_queue-0.0.3.dist-info/LICENSE
django_queue-0.0.3.dist-info/METADATA
django_queue-0.0.3.dist-info/WHEEL
django_queue-0.0.3.dist-info/top_level.txt
django_queue-0.0.3.dist-info/RECORD
